aiootp/__init__.py
aiootp/_debug_control.py
aiootp/_exceptions.py
aiootp/_gentools.py
aiootp/_paths.py
aiootp/__engagement/__init__.py
aiootp/__engagement/issue_reporting.py
aiootp/_constants/__init__.py
aiootp/_constants/datasets.py
aiootp/_constants/misc.py
aiootp/_permutations/__init__.py
aiootp/_permutations/affine_permutation.py
aiootp/_permutations/affine_permutation_config.py
aiootp/_permutations/affine_xor_chain.py
aiootp/_permutations/affine_xor_chain_config.py
aiootp/_permutations/fast_affine_xor_chain.py
aiootp/_typing/__init__.py
aiootp/_typing/_asynchs.py
aiootp/_typing/_ciphers.py
aiootp/_typing/_commons.py
aiootp/_typing/_databases.py
aiootp/_typing/_generics.py
aiootp/_typing/_keygens.py
aiootp/_typing/_paths.py
aiootp/_typing/_permutations.py
aiootp/_typing/_randoms.py
aiootp/_typing/interface.py
aiootp/_typing/tuples.py
aiootp/asynchs/__init__.py
aiootp/asynchs/aos.py
aiootp/asynchs/clocks.py
aiootp/asynchs/concurrency_interface.py
aiootp/asynchs/loops.py
aiootp/asynchs/processes.py
aiootp/asynchs/threads.py
aiootp/ciphers/__init__.py
aiootp/ciphers/chunky_2048.py
aiootp/ciphers/chunky_2048_config.py
aiootp/ciphers/cipher_interface.py
aiootp/ciphers/cipher_kdfs.py
aiootp/ciphers/cipher_stream_properties.py
aiootp/ciphers/cipher_streams.py
aiootp/ciphers/ciphertext_formatting.py
aiootp/ciphers/decipher_streams.py
aiootp/ciphers/dual_output_shake_cipher.py
aiootp/ciphers/dual_output_shake_cipher_config.py
aiootp/ciphers/key_bundle.py
aiootp/ciphers/padding.py
aiootp/ciphers/shake_permute_cipher.py
aiootp/ciphers/shake_permute_cipher_config.py
aiootp/ciphers/slick_256.py
aiootp/ciphers/slick_256_config.py
aiootp/ciphers/stream_hmac.py
aiootp/ciphers/stream_junction.py
aiootp/ciphers/synthetic_iv.py
aiootp/commons/__init__.py
aiootp/commons/configs.py
aiootp/commons/instances.py
aiootp/commons/namespaces.py
aiootp/commons/packaging.py
aiootp/commons/slots.py
aiootp/commons/typed_slots.py
aiootp/databases/__init__.py
aiootp/databases/async_database.py
aiootp-0.23.17.dist-info/licenses/LICENSE
aiootp-0.23.17.dist-info/METADATA
aiootp-0.23.17.dist-info/WHEEL
aiootp-0.23.17.dist-info/top_level.txt
aiootp-0.23.17.dist-info/RECORD
