Metadata-Version: 2.4
Name: aiootp
Version: 0.23.17
Summary: a high-level async cryptographic anonymity library to scale, simplify, & automate privacy best practices for secure data & identity processing, communication, & storage.
Author-email: "Gonzo Investigative Journalism Agency, LLC" <gonzo.development@protonmail.ch>, Ricchi Machado <rmlibre@riseup.net>
Maintainer-email: Ricchi Machado <rmlibre@riseup.net>
License-Expression: AGPL-3.0-only
Project-URL: Homepage, https://twitter.com/aiootp
Project-URL: Download, https://pypi.org/project/aiootp
Project-URL: Source, https://github.com/rmlibre/aiootp
Project-URL: Repository, https://github.com/rmlibre/aiootp.git
Project-URL: Tracker, https://github.com/rmlibre/aiootp/issues
Project-URL: Changelog, https://github.com/rmlibre/aiootp/blob/main/CHANGES.rst
Project-URL: Documentation, https://github.com/rmlibre/aiootp/blob/main/README.rst
Keywords: xor,key,salt,pepper,nonce,aad,iv,siv,resuse,misuse,robust,fully,context,committing,commitment,online,AEAD,auth,authenticated,authentication,shmac,hmac,nmac,mac,digest,integrity,infosec,opsec,appsec,privacy,engineering,stream,block,cipher,permutation,chunky2048,slick256,encrypt,plaintext,decrypt,ciphertext,passcrypt,passphrase,PBKDF,password,based,derivation,function,3dh,2dh,25519,x25519,ed25519,curve25519,diffie,hellman,sign,signature,verify,verification,db,database,value,store,user,uu
Classifier: Development Status :: 4 - Beta
Classifier: Framework :: AsyncIO
Classifier: Framework :: IPython
Classifier: Framework :: Jupyter
Classifier: Framework :: Pytest
Classifier: Natural Language :: English
Classifier: Operating System :: Other OS
Classifier: Operating System :: Unix
Classifier: Operating System :: MacOS
Classifier: Operating System :: MacOS :: MacOS X
Classifier: Operating System :: POSIX
Classifier: Operating System :: POSIX :: BSD
Classifier: Operating System :: POSIX :: Linux
Classifier: Operating System :: OS Independent
Classifier: Operating System :: Microsoft :: Windows
Classifier: Topic :: System
Classifier: Topic :: Internet
Classifier: Topic :: Security
Classifier: Topic :: Database
Classifier: Topic :: Education
Classifier: Topic :: Utilities
Classifier: Topic :: Communications
Classifier: Topic :: Office/Business
Classifier: Topic :: Text Processing
Classifier: Topic :: System :: Archiving
Classifier: Topic :: Internet :: WWW/HTTP
Classifier: Topic :: Software Development
Classifier: Topic :: System :: Networking
Classifier: Topic :: System :: Filesystems
Classifier: Topic :: Communications :: Chat
Classifier: Topic :: Scientific/Engineering
Classifier: Topic :: Communications :: Email
Classifier: Topic :: Security :: Cryptography
Classifier: Topic :: Office/Business :: Financial
Classifier: Topic :: Communications :: File Sharing
Classifier: Topic :: System :: Distributed Computing
Classifier: Topic :: System :: Software Distribution
Classifier: Topic :: System :: Systems Administration
Classifier: Topic :: Software Development :: Libraries
Classifier: Topic :: Scientific/Engineering :: Mathematics
Classifier: Topic :: Office/Business :: Financial :: Investment
Classifier: Topic :: Office/Business :: Financial :: Accounting
Classifier: Topic :: Software Development :: Libraries :: Python Modules
Classifier: Topic :: Software Development :: Libraries :: Application Frameworks
Classifier: Typing :: Typed
Classifier: Programming Language :: Python
Classifier: Programming Language :: Python :: 3
Classifier: Programming Language :: Python :: 3 :: Only
Classifier: Programming Language :: Python :: 3.9
Classifier: Programming Language :: Python :: 3.10
Classifier: Programming Language :: Python :: 3.11
Classifier: Programming Language :: Python :: 3.12
Classifier: Programming Language :: Python :: 3.13
Classifier: Programming Language :: Python :: Implementation :: CPython
Classifier: Programming Language :: Python :: Implementation :: PyPy
Classifier: Intended Audience :: Education
Classifier: Intended Audience :: Developers
Classifier: Intended Audience :: Legal Industry
Classifier: Intended Audience :: Other Audience
Classifier: Intended Audience :: Science/Research
Classifier: Intended Audience :: End Users/Desktop
Classifier: Intended Audience :: Healthcare Industry
Classifier: Intended Audience :: System Administrators
Classifier: Intended Audience :: Information Technology
Classifier: Intended Audience :: Telecommunications Industry
Classifier: Intended Audience :: Financial and Insurance Industry
Requires-Python: >=3.9
License-File: LICENSE
Requires-Dist: aiofiles>=24.1.0
Requires-Dist: cryptography>=45.0.6
Provides-Extra: test
Requires-Dist: coverage[toml]>=7.10.4; extra == "test"
Requires-Dist: hypothesis>=6.138.2; extra == "test"
Requires-Dist: pytest>=8.4.1; extra == "test"
Requires-Dist: pytest-asyncio>=1.1.0; extra == "test"
Requires-Dist: ruff>=0.12.10; extra == "test"
Provides-Extra: dev
Requires-Dist: build>=1.3.0; extra == "dev"
Requires-Dist: coverage[toml]>=7.10.4; extra == "dev"
Requires-Dist: hypothesis>=6.138.2; extra == "dev"
Requires-Dist: ipython>=8.18.1; extra == "dev"
Requires-Dist: pytest>=8.4.1; extra == "dev"
Requires-Dist: pytest-asyncio>=1.1.0; extra == "dev"
Requires-Dist: ruff>=0.12.10; extra == "dev"
Requires-Dist: setuptools>=80.9.0; extra == "dev"
Requires-Dist: twine>=6.1.0; extra == "dev"
Requires-Dist: wheel>=0.45.1; extra == "dev"
Dynamic: license-file
